example_pkg/__init__.py
example_pkg/module.py
example_pkg_danteese/__init__.py
example_pkg_danteese/module.py
example_pkg_danteese-0.1.0.dist-info/LICENSE
example_pkg_danteese-0.1.0.dist-info/METADATA
example_pkg_danteese-0.1.0.dist-info/WHEEL
example_pkg_danteese-0.1.0.dist-info/top_level.txt
example_pkg_danteese-0.1.0.dist-info/RECORD
